topsis/__init__.py
topsis/topsis.py
topsis_anjani_102303480-1.0.0.dist-info/METADATA
topsis_anjani_102303480-1.0.0.dist-info/WHEEL
topsis_anjani_102303480-1.0.0.dist-info/top_level.txt
topsis_anjani_102303480-1.0.0.dist-info/RECORD
