Metadata-Version: 2.4
Name: Topsis-Anjani-102303480
Version: 1.0.0
Summary: TOPSIS implementation in Python
Author: Anjani Agarwal
Requires-Dist: numpy
Requires-Dist: pandas
Dynamic: author
Dynamic: description
Dynamic: description-content-type
Dynamic: requires-dist
Dynamic: summary
